dl_ext/__init__.py
dl_ext/average_meter.py
dl_ext/file_ext.py
dl_ext/nlp_ext.py
dl_ext/primitive.py
dl_ext/timer.py
dl_ext/version.py
dl_ext/pytorch_ext/__init__.py
dl_ext/pytorch_ext/dist.py
dl_ext/pytorch_ext/optim.py
dl_ext/pytorch_ext/sampler.py
dl_ext/pytorch_ext/nn/__init__.py
dl_ext/pytorch_ext/nn/modules/__init__.py
dl_ext/pytorch_ext/nn/modules/loss.py
dl_ext/vision_ext/__init__.py
dl_ext/vision_ext/basic.py
dl_ext/vision_ext/conv.py
dl_ext/vision_ext/project.py
dl_ext/vision_ext/transforms.py
dl_ext/vision_ext/datasets/__init__.py
dl_ext/vision_ext/datasets/kitti/__init__.py
dl_ext/vision_ext/datasets/kitti/utils.py
dl_ext/vision_ext/datasets/kitti/io/__init__.py
dl_ext/vision_ext/datasets/kitti/io/_image.py
dl_ext/vision_ext/datasets/kitti/io/_label.py
dl_ext/vision_ext/datasets/kitti/io/calib.py
dl_ext/vision_ext/datasets/kitti/io/image_2.py
dl_ext/vision_ext/datasets/kitti/io/image_3.py
dl_ext/vision_ext/datasets/kitti/io/image_info.py
dl_ext/vision_ext/datasets/kitti/io/label_2.py
dl_ext/vision_ext/datasets/kitti/io/label_3.py
dl_ext/vision_ext/datasets/kitti/io/velodyne.py
dl_ext/vision_ext/datasets/kitti/structures/__init__.py
dl_ext/vision_ext/datasets/kitti/structures/calib.py
dl_ext/vision_ext/datasets/kitti/structures/kitti_object_3d.py
dl_ext/vision_ext/models/__init__.py
dl_ext/vision_ext/models/resnet.py
dl_ext/vision_ext/models/pointnet/__init__.py
dl_ext/vision_ext/models/pointnet/model.py
dl_ext/vision_ext/models/psmnet/__init__.py
dl_ext/vision_ext/models/psmnet/basic.py
dl_ext/vision_ext/models/psmnet/stackhourglass.py
dl_ext/vision_ext/models/psmnet/submodule.py
dl_ext-1.3.4.dist-info/METADATA
dl_ext-1.3.4.dist-info/WHEEL
dl_ext-1.3.4.dist-info/top_level.txt
dl_ext-1.3.4.dist-info/RECORD
