Metadata-Version: 2.1
Name: dl-ext
Version: 1.3.4
Summary: Chen Linghao's personal utils.
Home-page: UNKNOWN
Author: UNKNOWN
Author-email: UNKNOWN
License: UNKNOWN
Platform: UNKNOWN
Requires-Dist: numpy
Requires-Dist: tensorboard
Requires-Dist: tensorboardX
Requires-Dist: torchvision
Requires-Dist: multipledispatch
Requires-Dist: requests
Requires-Dist: tqdm
Requires-Dist: termcolor
Requires-Dist: matplotlib
Requires-Dist: Pillow
Requires-Dist: colorama
